{"kind":"APIResourceList","apiVersion":"v1","groupVersion":"cert-manager.io/v1","resources":[{"name":"certificaterequests","singularName":"certificaterequest","namespaced":true,"group":"cert-manager.io","version":"v1","kind":"CertificateRequest","verbs":["delete","deletecollection","get","list","patch","create","update","watch"],"shortNames":["cr","crs"],"categories":["cert-manager"]},{"name":"certificaterequests/status","singularName":"certificaterequest","namespaced":true,"group":"cert-manager.io","version":"v1","kind":"CertificateRequest","verbs":["get","patch","update"]},{"name":"certificates","singularName":"certificate","namespaced":true,"group":"cert-manager.io","version":"v1","kind":"Certificate","verbs":["delete","deletecollection","get","list","patch","create","update","watch"],"shortNames":["cert","certs"],"categories":["cert-manager"]},{"name":"certificates/status","singularName":"certificate","namespaced":true,"group":"cert-manager.io","version":"v1","kind":"Certificate","verbs":["get","patch","update"]},{"name":"clusterissuers","singularName":"clusterissuer","namespaced":false,"group":"cert-manager.io","version":"v1","kind":"ClusterIssuer","verbs":["delete","deletecollection","get","list","patch","create","update","watch"],"categories":["cert-manager"]},{"name":"clusterissuers/status","singularName":"clusterissuer","namespaced":false,"group":"cert-manager.io","version":"v1","kind":"ClusterIssuer","verbs":["get","patch","update"]},{"name":"issuers","singularName":"issuer","namespaced":true,"group":"cert-manager.io","version":"v1","kind":"Issuer","verbs":["delete","deletecollection","get","list","patch","create","update","watch"],"categories":["cert-manager"]},{"name":"issuers/status","singularName":"issuer","namespaced":true,"group":"cert-manager.io","version":"v1","kind":"Issuer","verbs":["get","patch","update"]}]}
